aquariumlearning/__init__.py
aquariumlearning/base_labels.py
aquariumlearning/class_map.py
aquariumlearning/client.py
aquariumlearning/collection_client.py
aquariumlearning/coordinate_frames.py
aquariumlearning/dataset.py
aquariumlearning/dataset_client.py
aquariumlearning/datasets.py
aquariumlearning/datasharing.py
aquariumlearning/embedding_distance_sampling.py
aquariumlearning/frames.py
aquariumlearning/inference.py
aquariumlearning/inferences.py
aquariumlearning/issues.py
aquariumlearning/labels.py
aquariumlearning/metrics_manager.py
aquariumlearning/modified_labels.py
aquariumlearning/sampling_agent.py
aquariumlearning/segments.py
aquariumlearning/sensor_data.py
aquariumlearning/turbo.py
aquariumlearning/util.py
aquariumlearning/viridis.py
aquariumlearning/work_queues.py
aquariumlearning-1.0.7.dist-info/METADATA
aquariumlearning-1.0.7.dist-info/WHEEL
aquariumlearning-1.0.7.dist-info/top_level.txt
aquariumlearning-1.0.7.dist-info/RECORD
